{
  "1": {
    "lv": 10,
    "award": "202:500"
  },
  "2": {
    "lv": 20,
    "award": "202:1000"
  },
  "3": {
    "lv": 30,
    "award": "202:1000"
  },
  "4": {
    "lv": 40,
    "award": "202:1500"
  },
  "5": {
    "lv": 50,
    "award": "202:1500"
  },
  "6": {
    "lv": 60,
    "award": "202:2000"
  },
  "7": {
    "lv": 70,
    "award": "202:2000"
  },
  "8": {
    "lv": 80,
    "award": "202:2500"
  },
  "9": {
    "lv": 90,
    "award": "202:2500"
  },
  "10": {
    "lv": 100,
    "award": "202:3000"
  }
}